definedfunctions/__init__.py
definedfunctions-0.2.dist-info/LICENSE.txt
definedfunctions-0.2.dist-info/METADATA
definedfunctions-0.2.dist-info/WHEEL
definedfunctions-0.2.dist-info/top_level.txt
definedfunctions-0.2.dist-info/RECORD
