Metadata-Version: 2.1
Name: definedfunctions
Version: 0.2
Summary: Package contains all pre defined progamming's task
Home-page: UNKNOWN
Author: VaibhavChopra
Author-email: vaibhavchopra1408@gmail.com
License: UNKNOWN
Platform: UNKNOWN
Classifier: Programming Language :: Python :: 3
Classifier: License :: OSI Approved :: MIT License
Classifier: Operating System :: OS Independent
License-File: LICENSE.txt
